[{"id":"2","name":"\u4e66    \u8bb0\uff1a\u90d1\u541b\u793c","telnum":"82426108","depart":"1"},{"id":"3","name":"\u6821    \u957f\uff1a\u67f3\u8d21\u6167","telnum":"82426101","depart":"1"},{"id":"4","name":"\u526f \u4e66 \u8bb0\uff1a\u6768  \u519b","telnum":"82426109","depart":"1"},{"id":"5","name":"\u526f \u4e66 \u8bb0\uff1a\u5218\u7b71\u6bc5","telnum":"82426103","depart":"1"},{"id":"6","name":"\u7eaa\u59d4\u4e66\u8bb0\uff1a\u51af\u6653\u6625","telnum":"82426107","depart":"1"},{"id":"7","name":"\u526f \u6821 \u957f\uff1a\u51af\u559c\u6625","telnum":"82426102","depart":"1"},{"id":"8","name":"\u526f \u6821 \u957f\uff1a\u97e9\u79cb\u5b9e","telnum":"82426105","depart":"1"},{"id":"9","name":"\u526f \u6821 \u957f\uff1a\u5218  \u52c7","telnum":"82426802","depart":"1"},{"id":"10","name":"\u526f \u6821 \u957f\uff1a\u8bb8\u6653\u9769","telnum":"82427118","depart":"1"},{"id":"11","name":"\u526f \u6821 \u957f\uff1a\u5f6d\u658c\u67cf","telnum":"82426104","depart":"1"},{"id":"12","name":"\u526f \u6821 \u957f\uff1a\u8bb8\u5b9d\u6770","telnum":"82427103","depart":"1"},{"id":"13","name":"\u526f \u6821 \u957f\uff1a\u9676\u5fd7\u7ea2","telnum":"82427187","depart":"1"},{"id":"15","name":"\u515a\u59d4\u5e38\u59d4\u517c\u7ec4\u7ec7\u90e8\u90e8\u957f:\u90b5\u957f\u751f","telnum":"82426805","depart":"2"},{"id":"17","name":"\u4e3b\u4efb\u5ba4","telnum":"82426818","depart":"3"},{"id":"18","name":"\u526f\u4e3b\u4efb\u5ba4","telnum":"82426800","depart":"3"},{"id":"19","name":"\u526f\u4e3b\u4efb\u5ba4","telnum":"82426819","depart":"3"},{"id":"20","name":"\u526f\u4e3b\u4efb\u5ba4","telnum":"82426817","depart":"3"},{"id":"21","name":"\u673a\u8981\u5ba4","telnum":"82426800","depart":"3"},{"id":"22","name":"\u6587\u6cd5\u4e8b\u52a1\u5ba4","telnum":"82426814","depart":"3"},{"id":"23","name":"\u6587\u5370\u5ba4","telnum":"82426812","depart":"3"},{"id":"24","name":"\u884c\u653f\u529e\u516c\u5ba4","telnum":"82426815","depart":"3"},{"id":"25","name":"\u7efc\u5408\u529e\u516c\u5ba4","telnum":"82427128","depart":"3"},{"id":"26","name":"\u4fe1\u8bbf\u3001\u7763\u529e","telnum":"82426801","depart":"3"},{"id":"27","name":"\u7efc\u5408\u6863\u6848\u5ba4","telnum":"82426845","depart":"3"},{"id":"28","name":"\u7efc\u5408\u6863\u6848\u5ba4","telnum":"82427175","depart":"3"},{"id":"29","name":"\u53f8\u673a\u73ed","telnum":"82427177","depart":"3"},{"id":"30","name":"\u4f20\u771f","telnum":"62913394","depart":"3"},{"id":"32","name":"\u90e8\u957f\u5ba4","telnum":"82426805","depart":"4"},{"id":"33","name":"\u526f\u90e8\u957f\u5ba4","telnum":"82426804","depart":"4"},{"id":"34","name":"\u529e\u516c\u5ba4\uff08\u5e72\u90e8\uff09","telnum":"82426803","depart":"4"},{"id":"35","name":"\u529e\u516c\u5ba4\uff08\u7ec4\u7ec7\u3001\u515a\u6821\uff09","telnum":"82426804","depart":"4"},{"id":"36","name":"\u4f20\u771f","telnum":"62939162","depart":"4"},{"id":"37","name":"\u5317\u4eac\u9ad8\u6821\u6559\u5e08\u515a\u5458\u5728\u7ebf\u5e73\u53f0\u8fd0\u884c\u7ba1\u7406","telnum":"62912201","depart":"4"},{"id":"38","name":"\u5317\u4eac\u9ad8\u6821\u6559\u5e08\u515a\u5458\u5728\u7ebf\u5e73\u53f0\u8fd0\u884c\u7ba1\u7406","telnum":"82427100","depart":"4"},{"id":"40","name":"\u90e8\u957f\u5ba4","telnum":"82426806","depart":"5"},{"id":"41","name":"\u526f\u90e8\u957f\/\u65b0\u95fb\u4e2d\u5fc3\u4e3b\u4efb\u5ba4","telnum":"82426843","depart":"5"},{"id":"42","name":"\u526f\u90e8\u957f\u5ba4","telnum":"","depart":"5"},{"id":"43","name":"\u7406\u8bba\u5b66\u4e60\u5ba4","telnum":"82426807","depart":"5"},{"id":"44","name":"\u6821\u62a5\u7f16\u8f91\u90e8","telnum":"82426808","depart":"5"},{"id":"45","name":"\u529e\u516c\u5ba4","telnum":"82426809","depart":"5"},{"id":"47","name":"\u4e3b\u4efb\u5ba4","telnum":"82426866","depart":"6"},{"id":"48","name":"\u529e\u516c\u5ba4","telnum":"82426865","depart":"6"},{"id":"50","name":"\u4e3b\u4efb\u5ba4","telnum":"82426844","depart":"7"},{"id":"52","name":"\u5904\u957f\u5ba4","telnum":"82426831","depart":"8"},{"id":"53","name":"\u526f\u5904\u957f\u5ba4","telnum":"82426823","depart":"8"},{"id":"54","name":"\u526f\u5904\u957f\u5ba4","telnum":"82426829","depart":"8"},{"id":"55","name":"\u526f\u5904\u957f\u5ba4","telnum":"82426137","depart":"8"},{"id":"56","name":"\u529e\u516c\u5ba4","telnum":"82426830","depart":"8"},{"id":"57","name":"\u6559\u5b66\u8fd0\u884c\u4e0e\u6210\u7ee9\u7ba1\u7406","telnum":"82426824","depart":"8"},{"id":"58","name":"\u5065\u7fd4\u6865\u6821\u533a\u6559\u5b66\u7ba1\u7406","telnum":"64884682","depart":"8"},{"id":"59","name":"\u6559\u52a1\u7ba1\u7406\u4fe1\u606f\u5316\u5efa\u8bbe","telnum":"82426822","depart":"8"},{"id":"60","name":"\u6392\u8bfe\u4e0e\u8003\u8bd5\u7ba1\u7406","telnum":"82426827","depart":"8"},{"id":"61","name":"\u4e13\u4e1a\u5efa\u8bbe\/\u8bfe\u7a0b\u4e0e\u6559\u6750\u5efa\u8bbe","telnum":"82426826","depart":"8"},{"id":"62","name":"\u5b9e\u8df5\u6559\u5b66\u5efa\u8bbe\uff08\u4e00\uff09","telnum":"82426825","depart":"8"},{"id":"63","name":"\u5b9e\u8df5\u6559\u5b66\u5efa\u8bbe\uff08\u4e8c\uff09","telnum":"82426828","depart":"8"},{"id":"64","name":"\u6559\u5b66\u8d28\u91cf\u76d1\u63a7","telnum":"82426883","depart":"8"},{"id":"65","name":"\u8bd5\u5377\u5e93","telnum":"82426929","depart":"8"},{"id":"66","name":"\u7535\u6559\u4e2d\u5fc3\uff08\u56fe\u4e66\u9986\u5341\u5c42\uff09","telnum":"82426992","depart":"8"},{"id":"67","name":"\u7535\u6559\u4e2d\u5fc3\uff08\u56fe\u4e66\u9986\u4e5d\u5c42\uff09","telnum":"82426993","depart":"8"},{"id":"68","name":"\u7535\u6559\u4e2d\u5fc3\uff08\u4e8c\u6559\u542c\u529b\u5ba4\uff09","telnum":"82426994","depart":"8"},{"id":"69","name":"\u7535\u6559\u4e2d\u5fc3\uff08\u5065\u7fd4\u6865\uff09","telnum":"64884698","depart":"8"},{"id":"70","name":"\u7535\u6559\u4e2d\u5fc3\uff08\u6e05\u6cb3\uff09","telnum":"62844819","depart":"8"},{"id":"71","name":"\u6559\u6750\u79d1\uff08\u5c0f\u8425\uff09","telnum":"82426988","depart":"8"},{"id":"72","name":"\u6559\u6750\u79d1\uff08\u5c0f\u8425\uff09","telnum":"82426128","depart":"8"},{"id":"73","name":"\u6559\u6750\u79d1\uff08\u5065\u7fd4\u6865\uff09","telnum":"64884683","depart":"8"},{"id":"74","name":"\u6559\u6750\u79d1\uff08\u6e05\u6cb3\uff09","telnum":"62844809","depart":"8"},{"id":"76","name":"\u5904\u957f\u5ba4","telnum":"82426832","depart":"9"},{"id":"77","name":"\u526f\u5904\u957f\/\u4ea7\u4e1a\u4e0e\u7ecf\u8425\u6027\u8d44\u4ea7\u7ba1\u7406\u529e\u516c\u5ba4","telnum":"82426833","depart":"9"},{"id":"78","name":"\u526f\u5904\u957f\u5ba4","telnum":"82426834","depart":"9"},{"id":"79","name":"\u529e\u516c\u5ba4","telnum":"82426134","depart":"9"},{"id":"80","name":"\u79d1\u7814\u79d1","telnum":"82426834","depart":"9"},{"id":"81","name":"\u5b66\u62a5\u7f16\u8f91\u90e8","telnum":"62939132","depart":"9"},{"id":"82","name":"\u4f20\u771f","telnum":"62917465","depart":"9"},{"id":"83","name":"\u673a\u7535\u7cfb\u7edf\u6d4b\u63a7\u91cd\u70b9\u5b9e\u9a8c\u5ba4","telnum":"82426991","depart":"9"},{"id":"84","name":"\u673a\u7535\u7cfb\u7edf\u6d4b\u63a7\u91cd\u70b9\u5b9e\u9a8c\u5ba4","telnum":"82427146","depart":"9"},{"id":"85","name":"\u673a\u7535\u7cfb\u7edf\u6d4b\u63a7\u91cd\u70b9\u5b9e\u9a8c\u5ba4","telnum":"62843743","depart":"9"},{"id":"86","name":"TRS\u8f6f\u4ef6\u5f00\u653e\u5b9e\u9a8c\u5ba4","telnum":"64878321","depart":"9"},{"id":"87","name":"(\u4e2d\u6587\u4fe1\u606f\u5904\u7406\u7814\u7a76\u4e2d\u5fc3)","telnum":"64859900","depart":"9"},{"id":"88","name":"\u4fe1\u606f\u83b7\u53d6\u4e0e\u68c0\u6d4b\u5b9e\u9a8c\u5ba4","telnum":"64884670","depart":"9"},{"id":"89","name":"\u4fe1\u606f\u83b7\u53d6\u4e0e\u68c0\u6d4b\u5b9e\u9a8c\u5ba4","telnum":"64884930","depart":"9"},{"id":"90","name":"\u6570\u636e\u6062\u590d\u7814\u7a76\u6240","telnum":"64884926","depart":"9"},{"id":"91","name":"\u5317\u4eac\u673a\u7535\u6280\u672f\u7814\u7a76\u6240","telnum":"65495672","depart":"9"},{"id":"92","name":"\u5317\u4eac\u610f\u5eb7\u673a\u68b0\u6709\u9650\u516c\u53f8","telnum":"61669817","depart":"9"},{"id":"93","name":"\u5317\u4eac\u62d3\u5c14\u601d\u4fe1\u606f\u6280\u672f\u6709\u9650\u516c\u53f8","telnum":"64859900","depart":"9"},{"id":"95","name":"\u4e3b\u4efb\u5ba4","telnum":"82426837","depart":"10"},{"id":"96","name":"\u4e66\u8bb0\/\u526f\u4e3b\u4efb\u5ba4","telnum":"82426838","depart":"10"},{"id":"97","name":"\u526f\u4e3b\u4efb\u5ba4","telnum":"82426836","depart":"10"},{"id":"98","name":"\u7814\u7a76\u751f\u5de5\u4f5c\u529e\u516c\u5ba4","telnum":"82426835","depart":"10"},{"id":"99","name":"\u57f9\u517b\u4e0e\u5b66\u7c4d\/\u62db\u751f\u4e0e\u5c31\u4e1a\u529e\u516c\u5ba4","telnum":"82426836","depart":"10"},{"id":"100","name":"\u57f9\u517b\u4e0e\u5b66\u7c4d\/\u62db\u751f\u4e0e\u5c31\u4e1a\u529e\u516c\u5ba4","telnum":"62843704","depart":"10"},{"id":"101","name":"\u5b66\u4f4d\u4e0e\u5b66\u79d1\u5efa\u8bbe\/\u884c\u653f\u529e\u516c\u5ba4","telnum":"82426838","depart":"10"},{"id":"103","name":"\u5904\u957f\u5ba4","telnum":"82426840","depart":"11"},{"id":"104","name":"\u526f\u5904\u957f\u5ba4","telnum":"82426130","depart":"11"},{"id":"105","name":"\u5e08\u8d44","telnum":"82426839","depart":"11"},{"id":"106","name":"\u8058\u4efb","telnum":"82427143","depart":"11"},{"id":"107","name":"\u8c03\u914d","telnum":"82426841","depart":"11"},{"id":"108","name":"\u52b3\u8d44","telnum":"82426842","depart":"11"},{"id":"109","name":"\u6863\u6848\u5ba4","telnum":"82426821","depart":"11"},{"id":"111","name":"\u5904\u957f\u5ba4","telnum":"82426850","depart":"12"},{"id":"112","name":"\u526f\u5904\u957f\u5ba4","telnum":"82426848","depart":"12"},{"id":"113","name":"\u4f1a\u8ba1\u79d1","telnum":"82426847","depart":"12"},{"id":"114","name":"\u9884\u7b97\u79d1","telnum":"82426848","depart":"12"},{"id":"115","name":"\u73b0\u91d1\u3001\u94f6\u884c\u51fa\u7eb3","telnum":"82426846","depart":"12"},{"id":"116","name":"\u8d22\u52a1\u62a5\u9500","telnum":"82426847","depart":"12"},{"id":"117","name":"\u8d22\u52a1\u62a5\u9500","telnum":"62939155","depart":"12"},{"id":"118","name":"\u5de5\u8d44\u7ba1\u7406","telnum":"82426849","depart":"12"},{"id":"119","name":"\u4e13\u9879\u8d44\u91d1\u7ba1\u7406","telnum":"82426849","depart":"12"},{"id":"120","name":"\u516c\u8d39\u533b\u7597\u7ba1\u7406","telnum":"62843765","depart":"12"},{"id":"121","name":"\u5de5\u4f1a\u7ecf\u8d39\u7ba1\u7406","telnum":"82426847","depart":"12"},{"id":"122","name":"\u79d1\u7814\u7ba1\u7406","telnum":"62939155","depart":"12"},{"id":"123","name":"\u5b66\u751f\u6536\u8d39\u7ba1\u7406","telnum":"62951926","depart":"12"},{"id":"124","name":"\u7f51\u7edc\u67e5\u8be2","telnum":"62951926","depart":"12"},{"id":"125","name":"\u5065\u7fd4\u6865\u8d22\u52a1","telnum":"64884720","depart":"12"},{"id":"127","name":"\u5904\u957f\u5ba4","telnum":"82426853","depart":"13"},{"id":"128","name":"\u526f\u5904\u957f\u5ba4","telnum":"82426855","depart":"13"},{"id":"129","name":"\u526f\u5904\u957f\u5ba4","telnum":"82426855","depart":"13"},{"id":"130","name":"\u5b66\u751f\u7ba1\u7406","telnum":"82426851","depart":"13"},{"id":"131","name":"\u5b66\u751f\u8d44\u52a9","telnum":"82426852","depart":"13"},{"id":"132","name":"\u5b66\u751f\u6559\u80b2\u4e0e\u670d\u52a1","telnum":"82426854","depart":"13"},{"id":"133","name":"\u5fc3\u7406\u54a8\u8be2\u4e2d\u5fc3\uff08\u5c0f\u8425\uff09","telnum":"62843778","depart":"13"},{"id":"134","name":"","telnum":"62843779","depart":"13"},{"id":"135","name":"\u5fc3\u7406\u54a8\u8be2\u4e2d\u5fc3\uff08\u5065\u7fd4\u6865\uff09","telnum":"64884741","depart":"13"},{"id":"136","name":"\u5fc3\u7406\u54a8\u8be2\u4e2d\u5fc3\uff08\u6e05\u6cb3\uff09","telnum":"62844815","depart":"13"},{"id":"138","name":"\u4e3b\u4efb\u5ba4","telnum":"82426856","depart":"14"},{"id":"139","name":"\u526f\u4e3b\u4efb\u5ba4","telnum":"82426129","depart":"14"},{"id":"140","name":"\u62db\u751f\u529e\u516c\u5ba4","telnum":"82426126","depart":"14"},{"id":"141","name":"\u62db\u751f\u529e\u516c\u5ba4","telnum":"62917339","depart":"14"},{"id":"142","name":"\u4f20\u771f","telnum":"62914528","depart":"14"},{"id":"143","name":"\u5c31\u4e1a\u529e\u516c\u5ba4","telnum":"82426857","depart":"14"},{"id":"144","name":"\u4f20\u771f","telnum":"62939190","depart":"14"},{"id":"146","name":"\u5904\u957f\u5ba4","telnum":"82426858","depart":"15"},{"id":"147","name":"\u529e\u516c\u5ba4","telnum":"62939325","depart":"15"},{"id":"148","name":"\u529e\u516c\u5ba4","telnum":"82426859","depart":"15"},{"id":"149","name":"\u7559\u5b66\u751f\u6559\u5b66\u529e\u516c\u5ba4","telnum":"62939131","depart":"15"},{"id":"150","name":"\u7559\u5b66\u751f\u516c\u5bd3","telnum":"82426987","depart":"15"},{"id":"151","name":"\u7559\u5b66\u751f\u516c\u5bd3","telnum":"62843780","depart":"15"},{"id":"152","name":"\u7559\u5b66\u751f\u516c\u5bd3","telnum":"62843781","depart":"15"},{"id":"153","name":"\u5916\u56fd\u4e13\u5bb6\u516c\u5bd3","telnum":"82426985","depart":"15"},{"id":"154","name":"\u5916\u56fd\u4e13\u5bb6\u516c\u5bd3","telnum":"82426986","depart":"15"},{"id":"156","name":"\u5904\u957f\u5ba4","telnum":"82426860","depart":"16"},{"id":"157","name":"\u529e\u516c\u5ba4","telnum":"82426861","depart":"16"},{"id":"158","name":"\u529e\u516c\u5ba4","telnum":"82426862","depart":"16"},{"id":"159","name":"\u529e\u516c\u5ba4(\u5065\u7fd4\u6865)","telnum":"64884668","depart":"16"},{"id":"161","name":"\u5904\u957f\u5ba4","telnum":"82426864","depart":"17"},{"id":"162","name":"\u529e\u516c\u5ba4","telnum":"82426863","depart":"17"},{"id":"164","name":"\u5904\u957f\u517c\u603b\u7ecf\u7406\u5ba4","telnum":"82426869","depart":"18"},{"id":"165","name":"\u603b\u652f\u4e66\u8bb0\u5ba4","telnum":"82427102","depart":"18"},{"id":"166","name":"\u526f\u5904\u957f\u517c\u526f\u603b\u7ecf\u7406\u5ba4","telnum":"82426956","depart":"18"},{"id":"167","name":"\u526f\u603b\u7ecf\u7406\u5ba4","telnum":"82426977","depart":"18"},{"id":"168","name":"\u526f\u603b\u7ecf\u7406\u5ba4","telnum":"82426957","depart":"18"},{"id":"169","name":"\u515a\u653f\u529e\u516c\u5ba4\uff08\u4e3b\u4efb\u5ba4\u3001\u515a\u52a1\u3001\u5206\u5de5\u4f1a\uff09","telnum":"82426968","depart":"18"},{"id":"170","name":"\u515a\u653f\u529e\u516c\u5ba4\uff08\u884c\u653f\uff0c\u4f20\u771f\uff09","telnum":"82426952","depart":"18"},{"id":"171","name":"\u7efc\u5408\u8d22\u52a1\u5ba4","telnum":"82426978","depart":"18"},{"id":"172","name":"\u5de5\u7a0b\u79d1","telnum":"82426867","depart":"18"},{"id":"173","name":"\u623f\u4ea7\u79d1","telnum":"82426870","depart":"18"},{"id":"174","name":"\u95e8\u8bca\u4e00\u90e8\u529e\u516c\u5ba4","telnum":"82426121","depart":"18"},{"id":"175","name":"\u95e8\u8bca\u4e00\u90e8\u5927\u5385","telnum":"82426983","depart":"18"},{"id":"176","name":"\u95e8\u8bca\u4e00\u90e8\u8ba1\u751f\u529e","telnum":"82426984","depart":"18"},{"id":"177","name":"\u95e8\u8bca\u4e00\u90e8\u4fdd\u5065\u529e","telnum":"82427144","depart":"18"},{"id":"178","name":"\u95e8\u8bca\u4e00\u90e8\uff08\u6e05\u6cb3\uff09","telnum":"62844979","depart":"18"},{"id":"179","name":"\u95e8\u8bca\u4e8c\u90e8\u529e\u516c\u5ba4","telnum":"64884870","depart":"18"},{"id":"180","name":"\u95e8\u8bca\u4e8c\u90e8\u503c\u73ed\u5ba4","telnum":"64884869","depart":"18"},{"id":"181","name":"\u95e8\u8bca\u4e8c\u90e8\u836f\u623f","telnum":"64879716","depart":"18"},{"id":"182","name":"\u8282\u80fd\u529e\u4e3b\u4efb\u5ba4","telnum":"82426971","depart":"18"},{"id":"183","name":"\u5065\u7fd4\u6865\u6821\u533a","telnum":"64884812","depart":"18"},{"id":"184","name":"\u6e05\u6cb3\u6821\u533a","telnum":"62844847","depart":"18"},{"id":"185","name":"\u4f9b\u6696\u90e8\u7ecf\u7406\u5ba4","telnum":"82426970","depart":"18"},{"id":"186","name":"\u5065\u7fd4\u6865\u6821\u533a","telnum":"64884867","depart":"18"},{"id":"187","name":"\u6e05\u6cb3\u6821\u533a","telnum":"62844846","depart":"18"},{"id":"188","name":"\u6821\u56ed\u90e8\u7ecf\u7406\u5ba4","telnum":"82426980","depart":"18"},{"id":"189","name":"\u5065\u7fd4\u6865\u6821\u533a","telnum":"64884871","depart":"18"},{"id":"190","name":"\u6e05\u6cb3\u6821\u533a","telnum":"62844986","depart":"18"},{"id":"191","name":"\u5c0f\u8425\u6536\u53d1\u5ba4","telnum":"82426982","depart":"18"},{"id":"192","name":"\u5065\u7fd4\u6865\u6536\u53d1\u5ba4","telnum":"64884876","depart":"18"},{"id":"193","name":"\u6e05\u6cb3\u6536\u53d1\u5ba4","telnum":"62844982","depart":"18"},{"id":"194","name":"\u7269\u4e1a\u90e8\u7ecf\u7406\u5ba4","telnum":"82426967","depart":"18"},{"id":"195","name":"\u5c0f\u8425\u4e00\u6559\u4f11\u606f\u5ba4","telnum":"82426989","depart":"18"},{"id":"196","name":"\u5c0f\u8425\u4e8c\u6559\u4f11\u606f\u5ba4","telnum":"82426990","depart":"18"},{"id":"197","name":"\u5c0f\u8425\u914d\u7535\u5ba4","telnum":"82426972","depart":"18"},{"id":"198","name":"\u5c0f\u8425\u7ef4\u4fee\u90e8","telnum":"82426969","depart":"18"},{"id":"199","name":"\u5c0f\u8425\u5b9e\u9a8c\u697c\u7535\u68af","telnum":"82426974","depart":"18"},{"id":"200","name":"\u5c0f\u8425\u5408\u5efa\u697c\u7535\u68af","telnum":"82426975","depart":"18"},{"id":"201","name":"\u5c0f\u8425\u7535\u68af\u7ef4\u4fee","telnum":"82426976","depart":"18"},{"id":"202","name":"\u5c0f\u8425\u56fe\u4e66\u9986\u7535\u68af","telnum":"82426115","depart":"18"},{"id":"203","name":"\u5c0f\u8425\u6e38\u6cf3\u6c60\u697c\u7535\u68af","telnum":"62843756","depart":"18"},{"id":"204","name":"\u6e05\u6cb3\u7ef4\u4fee\u90e8","telnum":"62844846","depart":"18"},{"id":"205","name":"\u6e05\u6cb3\u914d\u7535\u5ba4","telnum":"62844848","depart":"18"},{"id":"206","name":"\u5065\u7fd4\u6865\u7ef4\u4fee\u7ec4","telnum":"64884865","depart":"18"},{"id":"207","name":"\u5065\u7fd4\u6865\u914d\u7535\u5ba4","telnum":"64884866","depart":"18"},{"id":"208","name":"\u5065\u7fd4\u6865\u6559\u4e8c\u697c\u7535\u68af","telnum":"64879209","depart":"18"},{"id":"209","name":"\u5065\u7fd4\u6865\u56fe\u4e66\u9986\u7535\u68af","telnum":"64879201","depart":"18"},{"id":"210","name":"\u5c0f\u8425\u5357\u533a\u914d\u7535\u5ba4","telnum":"82426927","depart":"18"},{"id":"211","name":"\u516c\u5bd3\u90e8\u7ecf\u7406\u5ba4","telnum":"82426958","depart":"18"},{"id":"212","name":"\u5c0f\u8425\u6821\u533a\u516c\u5bd3\u529e\u516c\u5ba4","telnum":"82426959","depart":"18"},{"id":"213","name":"\u5c0f\u84251\u30012#\u697c\u95e8\u536b","telnum":"82426962","depart":"18"},{"id":"214","name":"\u5c0f\u84253#\u697c\u95e8\u536b","telnum":"82426963","depart":"18"},{"id":"215","name":"\u5c0f\u84254#\u697c\u95e8\u536b","telnum":"82426961","depart":"18"},{"id":"216","name":"\u5c0f\u84255#\u697c\u7535\u68af1","telnum":"82426964","depart":"18"},{"id":"217","name":"\u5c0f\u84255#\u697c\u7535\u68af2","telnum":"82426965","depart":"18"},{"id":"218","name":"\u6e05\u6cb3\u6821\u533a\u516c\u5bd3\u529e\u516c\u5ba4","telnum":"62844975","depart":"18"},{"id":"219","name":"\u6e05\u6cb3\u5b66\u4e00\u516c\u5bd3","telnum":"62844850","depart":"18"},{"id":"220","name":"\u6e05\u6cb3\u5b66\u4e8c\u516c\u5bd3","telnum":"62844864","depart":"18"},{"id":"221","name":"\u6e05\u6cb3\u5b66\u4e09\u516c\u5bd3","telnum":"62844978","depart":"18"},{"id":"222","name":"\u5065\u7fd4\u6865\u6821\u533a\u516c\u5bd3\u529e\u516c\u5ba4","telnum":"64884733","depart":"18"},{"id":"223","name":"\u5065\u7fd4\u6865\u5b66\u4e00\u516c\u5bd3","telnum":"64884977","depart":"18"},{"id":"224","name":"\u5065\u7fd4\u6865\u5b66\u4e8c\u516c\u5bd3","telnum":"64889405","depart":"18"},{"id":"225","name":"\u5065\u7fd4\u6865\u5b66\u56db\u516c\u5bd3","telnum":"64879541","depart":"18"},{"id":"226","name":"\u5065\u7fd4\u6865\u5b66\u4e00\u516c\u5bd3\u95e8\u536b","telnum":"64886631","depart":"18"},{"id":"227","name":"\u5065\u7fd4\u6865\u5b66\u4e8c\u516c\u5bd3\u95e8\u536b","telnum":"64884996","depart":"18"},{"id":"228","name":"\u5065\u7fd4\u6865\u5b66\u56db\u516c\u5bd3\u95e8\u536b","telnum":"64879541","depart":"18"},{"id":"229","name":"\u91c7\u8d2d\u90e8\u7ecf\u7406\u5ba4","telnum":"82427139","depart":"18"},{"id":"230","name":"\u996e\u98df\u90e8\u7ecf\u7406\u5ba4","telnum":"82426965","depart":"18"},{"id":"231","name":"\u5c0f\u8425\u6821\u533a\u529e\u516c\u5ba4","telnum":"82426953","depart":"18"},{"id":"232","name":"\u5c0f\u8425\u57fa\u672c\u4f19\u98df\u7ec4","telnum":"82426951","depart":"18"},{"id":"233","name":"\u5c0f\u8425\u91c7\u8d2d\u7ec4","telnum":"82426954","depart":"18"},{"id":"234","name":"\u5c0f\u8425\u9632\u706b\u76d1\u63a7\u5ba4","telnum":"62843782","depart":"18"},{"id":"235","name":"\u5c0f\u8425\u4e09\u697c\u9910\u5385","telnum":"82427184","depart":"18"},{"id":"236","name":"\u5065\u7fd4\u6865\u6821\u533a","telnum":"64884739","depart":"18"},{"id":"237","name":"\u6e05\u6cb3\u6821\u533a","telnum":"62844852","depart":"18"},{"id":"238","name":"\u8fd0\u8f93\u90e8\u7ecf\u7406\u5ba4","telnum":"82426979","depart":"18"},{"id":"239","name":"\u5065\u7fd4\u6865\u6821\u533a","telnum":"64884711","depart":"18"},{"id":"240","name":"\u4f01\u4e1a\u90e8\u7ecf\u7406\u5ba4","telnum":"82426981","depart":"18"},{"id":"241","name":"\u5c0f\u8425\u5546\u5e97","telnum":"62933122","depart":"18"},{"id":"242","name":"\u5c0f\u8425\u4e66\u5e97","telnum":"64941430","depart":"18"},{"id":"243","name":"\u5c0f\u8425\u773c\u955c\u5e97","telnum":"62957230","depart":"18"},{"id":"244","name":"\u5c0f\u8425\u62a5\u520a\u4ead","telnum":"62925787","depart":"18"},{"id":"245","name":"\u5065\u7fd4\u6865\u5370\u5237\u5382","telnum":"64884864","depart":"18"},{"id":"246","name":"\u5065\u7fd4\u6865\u7406\u53d1\u5e97","telnum":"64886638","depart":"18"},{"id":"247","name":"\u6e05\u6cb3\u7406\u53d1\u5e97","telnum":"62922018","depart":"18"},{"id":"248","name":"\u6e05\u6cb3\u5feb\u5ba2\u5370\u5237\u5382","telnum":"62844821","depart":"18"},{"id":"249","name":"\u91d1\u53f0\u8def\u62db\u5f85\u6240\u6240\u957f\u5ba4","telnum":"85992268","depart":"18"},{"id":"250","name":"\u91d1\u53f0\u8def\u62db\u5f85\u6240\u524d\u53f0","telnum":"85996852","depart":"18"},{"id":"252","name":"\u5904\u957f\u5ba4","telnum":"82426142","depart":"19"},{"id":"253","name":"\u526f\u5904\u957f\u5ba4","telnum":"82426995","depart":"19"},{"id":"254","name":"\u526f\u5904\u957f\u5ba4","telnum":"82426813","depart":"19"},{"id":"255","name":"\u529e\u516c\u5ba4","telnum":"82426996","depart":"19"},{"id":"256","name":"\u8ba1\u5212\u79d1","telnum":"82426997","depart":"19"},{"id":"257","name":"\u5de5\u7a0b\u79d1","telnum":"82426132","depart":"19"},{"id":"259","name":"\u5904\u957f\u5ba4","telnum":"82426873","depart":"20"},{"id":"260","name":"\u529e\u516c\u5ba4\uff08\u6237\u7c4d\uff09","telnum":"82426871","depart":"20"},{"id":"261","name":"\u5b89\u5168\u79d1\uff08\u6d88\u9632\u3001\u4ea4\u901a\uff09","telnum":"82426872","depart":"20"},{"id":"262","name":"\u6cbb\u5b89\u529e\u516c\u5ba4","telnum":"82426114","depart":"20"},{"id":"263","name":"\u56fe\u4e66\u9986\u697c\u503c\u73ed\u5ba4\uff08\u6280\u9632\u3001\u6d88\u9632\u62a5\u8b66\u7cfb\u7edf\uff09","telnum":"82426113","depart":"20"},{"id":"264","name":"\u5b66\u6821\u603b\u503c\u73ed\u5ba4","telnum":"82426888","depart":"20"},{"id":"265","name":"5\u53f7\u516c\u5bd3\u4e2d\u63a7\u5ba4","telnum":"82426110","depart":"20"},{"id":"266","name":"\u9632\u76d7\u76d1\u63a7\u4e13\u7528\u7ebf\u8def","telnum":"82426112","depart":"20"},{"id":"267","name":"\u5317\u6821\u95e8","telnum":"82426998","depart":"20"},{"id":"268","name":"\u4e1c\u6821\u95e8","telnum":"82426999","depart":"20"},{"id":"269","name":"\u5357\u6821\u533a\u4e1c\u95e8","telnum":"82426973","depart":"20"},{"id":"270","name":"\u4fdd\u5b89\u961f\u5bbf\u820d","telnum":"82426893","depart":"20"},{"id":"271","name":"\u5bb6\u59d4\u4f1a\u529e\u516c\u5ba4","telnum":"82426880","depart":"20"},{"id":"272","name":"\u5bb6\u59d4\u4f1a\u529e\u516c\u5ba4","telnum":"62939121","depart":"20"},{"id":"273","name":"\u5bb6\u5c5e\u9662\u4e1c\u95e8","telnum":"62939185","depart":"20"},{"id":"275","name":"\u6d88\u9632\u3001\u6cbb\u5b89","telnum":"64884735","depart":"21"},{"id":"276","name":"\u6d88\u9632\u3001\u6cbb\u5b89","telnum":"64867621","depart":"21"},{"id":"277","name":"\u6237\u7c4d\u3001\u4ea4\u901a","telnum":"64884734","depart":"21"},{"id":"278","name":"\u4e2d\u63a7\u5ba4","telnum":"64884734","depart":"21"},{"id":"279","name":"\u5357\u95e8","telnum":"64884875","depart":"21"},{"id":"280","name":"\u5317\u95e8","telnum":"64879295","depart":"21"},{"id":"281","name":"\u5b66\u751f\u56db\u516c\u5bd3\u95e8\u536b","telnum":"64879430","depart":"21"},{"id":"282","name":"\u6559\u4e00\u697c\u95e8\u536b","telnum":"64884684","depart":"21"},{"id":"283","name":"\u6559\u4e8c\u697c\u95e8\u536b","telnum":"64884669","depart":"21"},{"id":"284","name":"\u9632\u76d7\u76d1\u63a7\u4e13\u7528\u7ebf\u8def","telnum":"64884494","depart":"21"},{"id":"286","name":"\u6d88\u9632\u3001\u6cbb\u5b89\u3001\u4ea4\u901a\u3001\u6237\u7c4d","telnum":"62844813","depart":"22"},{"id":"287","name":"\u4e2d\u63a7\u5ba4","telnum":"62844814","depart":"22"},{"id":"288","name":"\u5357\u95e8","telnum":"62844985","depart":"22"},{"id":"289","name":"\u897f\u95e8","telnum":"62844983","depart":"22"},{"id":"290","name":"\u4fdd\u536b\u4f20\u771f","telnum":"62922534","depart":"22"},{"id":"291","name":"\u6559\u4e00\u697c\u9632\u76d7\u76d1\u63a7\u4e13\u7528\u7ebf\u8def","telnum":"62844884","depart":"22"},{"id":"292","name":"\u6559\u4e8c\u697c\u9632\u76d7\u76d1\u63a7\u4e13\u7528\u7ebf\u8def","telnum":"62844854","depart":"22"},{"id":"293","name":"\u5bb6\u59d4\u4f1a\u529e\u516c\u5ba4","telnum":"62844830","depart":"22"},{"id":"294","name":"\u5bb6\u5c5e\u9662\u95e8\u536b","telnum":"62844851","depart":"22"},{"id":"296","name":"\u4e3b\u4efb\u5ba4","telnum":"82426875","depart":"23"},{"id":"297","name":"\u7efc\u5408\u529e\u516c\u5ba4","telnum":"82426874","depart":"23"},{"id":"298","name":"\u8001\u5e72\u90e8\u6d3b\u52a8\u5ba4\uff08\u5c0f\u8425\uff09","telnum":"62939122","depart":"23"},{"id":"299","name":"\u8001\u5e72\u90e8\u6d3b\u52a8\u5ba4\uff08\u6e05\u6cb3\uff09","telnum":"62844984","depart":"23"},{"id":"300","name":"\u8001\u5e72\u90e8\u6d3b\u52a8\u5ba4\uff08\u91d1\u53f0\u8def\uff09","telnum":"85990079","depart":"23"},{"id":"302","name":"\u5e38\u52a1\u526f\u4e3b\u5e2d\u5ba4","telnum":"82426876","depart":"24"},{"id":"303","name":"\u526f\u4e3b\u5e2d\u5ba4","telnum":"82426889","depart":"24"},{"id":"304","name":"\u529e\u516c\u5ba4","telnum":"82426877","depart":"24"},{"id":"305","name":"\u6559\u5de5\u6d3b\u52a8\u4e2d\u5fc3","telnum":"62939118","depart":"24"},{"id":"307","name":"\u4e66\u8bb0\u5ba4","telnum":"62917338","depart":"25"},{"id":"308","name":"\u529e\u516c\u5ba4","telnum":"82426879","depart":"25"},{"id":"309","name":"\u529e\u516c\u5ba4","telnum":"82426881","depart":"25"},{"id":"311","name":"\u4e3b\u4efb\u5ba4","telnum":"82426895","depart":"26"},{"id":"313","name":"\u4e66\u8bb0\u5ba4","telnum":"82426810","depart":"27"},{"id":"315","name":"\u4e66\u8bb0\u5ba4","telnum":"64884661","depart":"28"},{"id":"317","name":"\u4e66\u8bb0\u5ba4","telnum":"82426811","depart":"29"},{"id":"319","name":"\u9662\u957f\u5ba4","telnum":"82427148","depart":"30"},{"id":"320","name":"\u4e66\u8bb0\u5ba4","telnum":"82427126","depart":"30"},{"id":"321","name":"\u526f\u9662\u957f\u5ba4","telnum":"82426820","depart":"30"},{"id":"322","name":"\u526f\u9662\u957f\u5ba4","telnum":"82426141","depart":"30"},{"id":"323","name":"\u526f\u4e66\u8bb0\u5ba4","telnum":"82427129","depart":"30"},{"id":"324","name":"\u5b66\u9662\u529e\u516c\u5ba4         ","telnum":"82426908","depart":"30"},{"id":"325","name":"\u6559\u5b66\u529e\u516c\u5ba4","telnum":"82426906","depart":"30"},{"id":"326","name":"\u7814\u7a76\u751f\u3001\u79d1\u7814","telnum":"82427149","depart":"30"},{"id":"327","name":"\u515a\u52a1\u3001\u5de5\u4f1a","telnum":"82427149","depart":"30"},{"id":"328","name":"\u5b66\u751f\u5de5\u4f5c\u529e\u516c\u5ba4","telnum":"82426907","depart":"30"},{"id":"329","name":"\u5c31\u4e1a\u6307\u5bfc\u670d\u52a1","telnum":"82426140","depart":"30"},{"id":"330","name":"\u673a\u68b0\u5236\u9020\u5b9e\u9a8c\u5ba4","telnum":"82427124","depart":"30"},{"id":"331","name":"\u673a\u68b0\u7535\u5b50\u5b9e\u9a8c\u5ba4","telnum":"82426909","depart":"30"},{"id":"332","name":"\u673a\u68b0\u8bbe\u8ba1\u5b9e\u9a8c\u5ba4","telnum":"82426910","depart":"30"},{"id":"333","name":"\u5de5\u4e1a\u8bbe\u8ba1\u5b9e\u9a8c\u5ba4","telnum":"82426911","depart":"30"},{"id":"334","name":"\u5de5\u4e1a\u5de5\u7a0b\u6559\u7814\u5ba4","telnum":"82426912","depart":"30"},{"id":"335","name":"\u8f66\u8f86\u5de5\u7a0b\u5b9e\u9a8c\u5ba4","telnum":"82426913","depart":"30"},{"id":"336","name":"\u5de5\u4e1a\u5de5\u7a0b\u5b9e\u9a8c\u5ba4","telnum":"82426914","depart":"30"},{"id":"337","name":"\u6c7d\u8f66\u7535\u5b50\u5b9e\u9a8c\u5ba4","telnum":"82427127","depart":"30"},{"id":"338","name":"\u667a\u80fd\u673a\u5668\u4eba\u7814\u7a76\u6240","telnum":"82427125","depart":"30"},{"id":"339","name":"\u53cc\u8058\u9662\u58eb\u529e\u516c\u5ba4","telnum":"82427173","depart":"30"},{"id":"341","name":"\u9662\u957f\u5ba4","telnum":"64884722","depart":"31"},{"id":"342","name":"\u4e66\u8bb0\u5ba4","telnum":"64884721","depart":"31"},{"id":"343","name":"\u5b66\u9662\u529e\u516c\u5ba4 ","telnum":"64884696","depart":"31"},{"id":"344","name":"\u5b66\u9662\u529e\u516c\u5ba4 ","telnum":"82426915","depart":"31"},{"id":"345","name":"\u5b66\u751f\u5de5\u4f5c\u529e\u516c\u5ba4","telnum":"64884697","depart":"31"},{"id":"346","name":"\u5b66\u751f\u5de5\u4f5c\u529e\u516c\u5ba4","telnum":"82426916","depart":"31"},{"id":"347","name":"\u7535\u5b50\u4fe1\u606f\u5de5\u7a0b\u7cfb\u529e\u516c\u5ba4","telnum":"64884717","depart":"31"},{"id":"348","name":"\u901a\u4fe1\u5de5\u7a0b\u7cfb\u529e\u516c\u5ba4","telnum":"64884695","depart":"31"},{"id":"349","name":"\u901a\u4fe1\u5de5\u7a0b\u7cfb\u529e\u516c\u5ba4","telnum":"64884700","depart":"31"},{"id":"350","name":"\u6d4b\u63a7\u6280\u672f\u4e0e\u4eea\u5668\u7cfb\u529e\u516c\u5ba4","telnum":"82426892","depart":"31"},{"id":"351","name":"\u5149\u4fe1\u606f\u79d1\u5b66\u4e0e\u6280\u672f\u7cfb\u529e\u516c\u5ba4","telnum":"82426917","depart":"31"},{"id":"352","name":"\u4eea\u5668\u5b66\u79d1\u529e\u516c\u5ba4","telnum":"82426918","depart":"31"},{"id":"353","name":"\u73b0\u4ee3\u6d4b\u8bd5\u6280\u672f\u7814\u7a76\u6240\u529e\u516c\u5ba4","telnum":"82426143","depart":"31"},{"id":"354","name":"\u73b0\u4ee3\u7535\u5b50\u6280\u672f\u5b9e\u9a8c\u5ba4\u529e\u516c\u5ba4","telnum":"82426919","depart":"31"},{"id":"356","name":"\u9662\u957f\u5ba4","telnum":"82427152","depart":"32"},{"id":"357","name":"\u9662\u957f\u5ba4","telnum":"64884716","depart":"32"},{"id":"358","name":"\u4e66\u8bb0\u5ba4","telnum":"82427153","depart":"32"},{"id":"359","name":"\u526f\u9662\u957f\u5ba4","telnum":"82427155","depart":"32"},{"id":"360","name":"\u526f\u4e66\u8bb0\u5ba4","telnum":"82427154","depart":"32"},{"id":"361","name":"\u7535\u5de5\u7535\u5b50\u5e38\u52a1\u526f\u4e3b\u4efb\u5ba4","telnum":"82427172","depart":"32"},{"id":"362","name":"\u7535\u5de5\u7535\u5b50\u5e38\u52a1\u526f\u4e3b\u4efb\u5ba4","telnum":"64884694","depart":"32"},{"id":"363","name":"\u5b66\u9662\u529e\u516c\u5ba4 ","telnum":"82427151","depart":"32"},{"id":"364","name":"\u5b66\u9662\u529e\u516c\u5ba4 ","telnum":"64884716","depart":"32"},{"id":"365","name":"\u5b66\u751f\u5de5\u4f5c\u529e\u516c\u5ba4","telnum":"82426921","depart":"32"},{"id":"366","name":"\u6559\u5b66\u7ba1\u7406\u529e\u516c\u5ba4","telnum":"82426920","depart":"32"},{"id":"367","name":"\u7535\u6c14\u5de5\u7a0b\u7cfb","telnum":"82427164","depart":"32"},{"id":"368","name":"\u7535\u5de5\u7535\u5b50\u5b9e\u9a8c\u6559\u5b66\u4e2d\u5fc3","telnum":"64884694","depart":"32"},{"id":"369","name":"\u7535\u5de5\u7535\u5b50\u5b9e\u9a8c\u6559\u5b66\u4e2d\u5fc3","telnum":"82426922","depart":"32"},{"id":"370","name":"\u63a7\u5236\u5de5\u7a0b\u7cfb","telnum":"82426924","depart":"32"},{"id":"371","name":"\u667a\u80fd\u79d1\u5b66\u4e0e\u6280\u672f\u7cfb","telnum":"82427140","depart":"32"},{"id":"373","name":"\u9662\u957f\u5ba4","telnum":"64884707","depart":"33"},{"id":"374","name":"\u4e66\u8bb0\u5ba4","telnum":"64884708","depart":"33"},{"id":"375","name":"\u5b66\u9662\u529e\u516c\u5ba4  ","telnum":"64879089","depart":"33"},{"id":"376","name":"\u6559\u5b66\u529e\u516c\u5ba4","telnum":"64884484","depart":"33"},{"id":"377","name":"\u6559\u5b66\u529e\u516c\u5ba4","telnum":"64884706","depart":"33"},{"id":"378","name":"\u5b66\u751f\u5de5\u4f5c\u529e\u516c\u5ba4","telnum":"64884712","depart":"33"},{"id":"379","name":"\u5b66\u751f\u5de5\u4f5c\u529e\u516c\u5ba4","telnum":"64884713","depart":"33"},{"id":"380","name":"\u5b66\u751f\u5de5\u4f5c\u529e\u516c\u5ba4","telnum":"82411924","depart":"33"},{"id":"381","name":"\u5b9e\u9a8c\u5ba4\u529e\u516c\u5ba4","telnum":"64884705","depart":"33"},{"id":"382","name":"\u673a\u623f","telnum":"64884681","depart":"33"},{"id":"383","name":"\u8ba1\u7b97\u673a\u79d1\u5b66\u4e0e\u6280\u672f\u7cfb","telnum":"64884114","depart":"33"},{"id":"384","name":"\u6559\u6388\u5de5\u4f5c\u5ba4","telnum":"64884709","depart":"33"},{"id":"385","name":"\u56fe\u50cf\u6280\u672f\u5de5\u4f5c\u5ba4","telnum":"64884710","depart":"33"},{"id":"386","name":"\u8ba1\u7b97\u673a\u5f00\u653e\u7cfb\u7edf\u5b9e\u9a8c\u5ba4","telnum":"64884878","depart":"33"},{"id":"387","name":"\u8ba1\u7b97\u673a\u5f00\u653e\u7cfb\u7edf\u5b9e\u9a8c\u5ba4","telnum":"64884879","depart":"33"},{"id":"388","name":"\u8f6f\u4ef6\u5de5\u7a0b\u7814\u7a76\u4e2d\u5fc3","telnum":"64872035","depart":"33"},{"id":"389","name":"JAVA\u5b9e\u9a8c\u5ba4","telnum":"64838741","depart":"33"},{"id":"390","name":"\u865a\u62df\u73b0\u5b9e\u4e0e\u7cfb\u7edf\u4eff\u771f\u7814\u7a76\u6240","telnum":"82427141","depart":"33"},{"id":"391","name":"\u667a\u80fd\u4fe1\u606f\u5904\u7406\u7814\u7a76\u6240","telnum":"82427145","depart":"33"},{"id":"393","name":"\u9662\u957f\u5ba4","telnum":"82427133","depart":"34"},{"id":"394","name":"\u4e66\u8bb0\u5ba4","telnum":"82427134","depart":"34"},{"id":"395","name":"\u526f\u9662\u957f\u5ba4","telnum":"82427136","depart":"34"},{"id":"396","name":"\u526f\u4e66\u8bb0\u5ba4","telnum":"82427137","depart":"34"},{"id":"397","name":"\u526f\u4e66\u8bb0\u5ba4","telnum":"62844810","depart":"34"},{"id":"398","name":"\u5b66\u9662\u529e\u516c\u5ba4 ","telnum":"82427131","depart":"34"},{"id":"399","name":"\u5b66\u9662\u529e\u516c\u5ba4 ","telnum":"82427138","depart":"34"},{"id":"400","name":"\u672c\u79d1\u6559\u5b66\u7ba1\u7406\u529e\u516c\u5ba4","telnum":"82426931","depart":"34"},{"id":"401","name":"\u672c\u79d1\u6559\u5b66\u7ba1\u7406\u529e\u516c\u5ba4","telnum":"82427130","depart":"34"},{"id":"402","name":"\u6559\u5b66\u7ba1\u7406\u3001\u7814\u7a76\u751f\u5de5\u4f5c\u529e\u516c\u5ba4","telnum":"82427135","depart":"34"},{"id":"403","name":"\u8f85\u5bfc\u5458\u529e\u516c\u5ba4\uff08\u5c0f\u8425\uff09","telnum":"82426901","depart":"34"},{"id":"404","name":"\u8f85\u5bfc\u5458\u529e\u516c\u5ba4\uff08\u5c0f\u8425\uff09","telnum":"82427132","depart":"34"},{"id":"405","name":"\u8f85\u5bfc\u5458\u529e\u516c\u5ba4\uff08\u6e05\u6cb3\uff09","telnum":"62844812","depart":"34"},{"id":"406","name":"\u4e13\u804c\u73ed\u4e3b\u4efb\u529e\u516c\u5ba4","telnum":"62844833","depart":"34"},{"id":"407","name":"\u515a\u5efa\u5de5\u4f5c\u3001\u8d44\u6599\u5ba4","telnum":"82426904","depart":"34"},{"id":"408","name":"\u77e5\u8bc6\u7ba1\u7406\u7814\u7a76\u57fa\u5730\u529e\u516c\u5ba4","telnum":"82426900","depart":"34"},{"id":"409","name":"\u5b9e\u9a8c\u7ecf\u6d4e\u5b66\u5b9e\u9a8c\u5ba4","telnum":"82426902","depart":"34"},{"id":"410","name":"\u4f1a\u8ba1\u4e0e\u8d22\u52a1\u5b9e\u9a8c\u5ba4","telnum":"82426903","depart":"34"},{"id":"411","name":"\u5b9e\u9a8c\u6559\u5b66\u4e2d\u5fc3\uff08\u5c0f\u8425\uff09","telnum":"82426905","depart":"34"},{"id":"412","name":"\u5b9e\u9a8c\u6559\u5b66\u4e2d\u5fc3\uff08\u6e05\u6cb3\uff09","telnum":"62844836","depart":"34"},{"id":"414","name":"\u9662\u957f\u5ba4        ","telnum":"82427171","depart":"35"},{"id":"415","name":"\u9662\u957f\u5ba4        ","telnum":"64884678","depart":"35"},{"id":"416","name":"\u4e66\u8bb0\u5ba4","telnum":"82427161","depart":"35"},{"id":"417","name":"\u4e66\u8bb0\u5ba4","telnum":"64884685","depart":"35"},{"id":"418","name":"\u526f\u9662\u957f\u5ba4","telnum":"82427169","depart":"35"},{"id":"419","name":"\u526f\u9662\u957f\u5ba4","telnum":"82427168","depart":"35"},{"id":"420","name":"\u526f\u4e66\u8bb0\u5ba4","telnum":"82427158","depart":"35"},{"id":"421","name":"\u603b\u652f\u529e\u516c\u5ba4","telnum":"82427161","depart":"35"},{"id":"422","name":"\u603b\u652f\u529e\u516c\u5ba4","telnum":"64884679","depart":"35"},{"id":"423","name":"\u5b66\u9662\u529e\u516c\u5ba4","telnum":"82427160","depart":"35"},{"id":"424","name":"\u5b66\u9662\u529e\u516c\u5ba4","telnum":"64884680","depart":"35"},{"id":"425","name":"\u6559\u52a1\u529e\u516c\u5ba4","telnum":"82427170","depart":"35"},{"id":"426","name":"\u6559\u52a1\u529e\u516c\u5ba4","telnum":"82427159","depart":"35"},{"id":"427","name":"\u6559\u52a1\u529e\u516c\u5ba4","telnum":"82427166","depart":"35"},{"id":"428","name":"\u5b66\u751f\u5de5\u4f5c\u529e\u516c\u5ba4","telnum":"82427157","depart":"35"},{"id":"429","name":"\u5b66\u751f\u5de5\u4f5c\u529e\u516c\u5ba4","telnum":"82427165","depart":"35"},{"id":"430","name":"\u56e2\u59d4\u5b66\u751f\u4f1a\u529e\u516c\u5ba4","telnum":"82427167","depart":"35"},{"id":"431","name":"\u5b9e\u9a8c\u5ba4","telnum":"64884677","depart":"35"},{"id":"432","name":"\u4fe1\u606f\u5b89\u5168\u5b9e\u9a8c\u5ba4","telnum":"82426135","depart":"35"},{"id":"433","name":"\u4fe1\u606f\u7cfb\u7edf\u5b9e\u9a8c\u5ba4","telnum":"82426136","depart":"35"},{"id":"435","name":"\u4e66\u8bb0\u5ba4","telnum":"82427104","depart":"36"},{"id":"436","name":"\u526f\u9662\u957f\u5ba4","telnum":"82427105","depart":"36"},{"id":"437","name":"\u526f\u9662\u957f\u5ba4","telnum":"82427110","depart":"36"},{"id":"438","name":"\u526f\u9662\u957f\u5ba4","telnum":"82427104","depart":"36"},{"id":"439","name":"\u526f\u4e66\u8bb0\u5ba4","telnum":"82427162","depart":"36"},{"id":"440","name":"\u5b66\u9662\u529e\u516c\u5ba4 ","telnum":"82427107","depart":"36"},{"id":"441","name":"\u6559\u5b66\u529e\u516c\u5ba4","telnum":"82427109","depart":"36"},{"id":"442","name":"\u5b66\u751f\u5de5\u4f5c\u529e\u516c\u5ba4","telnum":"82426926","depart":"36"},{"id":"443","name":"\u8d44\u6599\u5ba4","telnum":"82426925","depart":"36"},{"id":"444","name":"\u673a\u623f","telnum":"82427163","depart":"36"},{"id":"445","name":"\u529e\u516c\u5ba4\uff08\u5065\u7fd4\u6865\uff09","telnum":"64884729","depart":"36"},{"id":"447","name":"\u9662\u957f\u5ba4","telnum":"82427111","depart":"37"},{"id":"448","name":"\u4e66\u8bb0\u5ba4","telnum":"82427112","depart":"37"},{"id":"449","name":"\u526f\u9662\u957f\u5ba4","telnum":"82426955","depart":"37"},{"id":"450","name":"\u526f\u4e66\u8bb0\u5ba4","telnum":"82426127","depart":"37"},{"id":"451","name":"\u5b66\u9662\u529e\u516c\u5ba4 ","telnum":"82427114","depart":"37"},{"id":"452","name":"\u5b66\u751f\u5de5\u4f5c\u529e\u516c\u5ba4","telnum":"82426120","depart":"37"},{"id":"453","name":"\u6559\u52a1\u529e\u516c\u5ba4","telnum":"82427115","depart":"37"},{"id":"454","name":"\u82f1\u8bed\u6559\u7814\u5ba4\uff08\u5065\u7fd4\u6865\uff09","telnum":"64884704","depart":"37"},{"id":"455","name":"\u82f1\u8bed\u6559\u7814\u5ba4\uff08\u6e05\u6cb3\uff09","telnum":"62844825","depart":"37"},{"id":"457","name":"\u9662\u957f\u5ba4","telnum":"62843783","depart":"38"},{"id":"458","name":"\u4e66\u8bb0\u5ba4","telnum":"82427122","depart":"38"},{"id":"459","name":"\u526f\u9662\u957f\u5ba4","telnum":"82427121","depart":"38"},{"id":"460","name":"\u526f\u4e66\u8bb0\u5ba4","telnum":"82426937","depart":"38"},{"id":"461","name":"\u5b66\u751f\u5de5\u4f5c\u529e\u516c\u5ba4","telnum":"82427123","depart":"38"},{"id":"462","name":"\u884c\u653f\u529e\u516c\u5ba4","telnum":"82426111","depart":"38"},{"id":"463","name":"\u6559\u52a1\u529e\u516c\u5ba4","telnum":"82427119","depart":"38"},{"id":"464","name":"","telnum":"82427120","depart":"38"},{"id":"465","name":"\u6570\u5b66\u7cfb","telnum":"82426934","depart":"38"},{"id":"466","name":"\u6570\u5b66\u6559\u7814\u5ba4\uff08\u6e05\u6cb3\uff09","telnum":"62844827","depart":"38"},{"id":"467","name":"\u6570\u5b66\u5b9e\u9a8c\u5ba4\uff08\u5065\u7fd4\u6865\uff09","telnum":"64884699","depart":"38"},{"id":"468","name":"\u7edf\u8ba1\u7cfb","telnum":"82426934","depart":"38"},{"id":"469","name":"\u7269\u7406\u4e0e\u7535\u5b50\u79d1\u5b66\u7cfb","telnum":"82426935","depart":"38"},{"id":"470","name":"","telnum":"82426936","depart":"38"},{"id":"471","name":"\u7406\u7efc\u5b9e\u9a8c\u5ba4","telnum":"82426938","depart":"38"},{"id":"472","name":"","telnum":"62939128","depart":"38"},{"id":"473","name":"\u5927\u5b66\u7269\u7406\u5b9e\u9a8c\u4e2d\u5fc3","telnum":"82426932","depart":"38"},{"id":"474","name":"","telnum":"64884703","depart":"38"},{"id":"475","name":"\u6559\u6388\u5de5\u4f5c\u5ba4\uff08\u5065\u7fd4\u6865\uff09","telnum":"64884702","depart":"38"},{"id":"476","name":"\u4f20\u611f\u6280\u672f\u7814\u7a76\u4e2d\u5fc3","telnum":"64884673","depart":"38"},{"id":"477","name":"","telnum":"64884674","depart":"38"},{"id":"478","name":"\u5e94\u7528\u6570\u5b66\u7814\u7a76\u6240","telnum":"64884671","depart":"38"},{"id":"480","name":"\u4e3b\u4efb\u5ba4","telnum":"82427117","depart":"39"},{"id":"481","name":"\u4e66\u8bb0\u5ba4","telnum":"82427117","depart":"39"},{"id":"482","name":"\u529e\u516c\u5ba4","telnum":"82426939","depart":"39"},{"id":"483","name":"\u6559\u7814\u5ba4\uff08\u5c0f\u8425\uff09","telnum":"62939270","depart":"39"},{"id":"484","name":"\u6559\u7814\u5ba4\uff08\u5065\u7fd4\u6865\uff09","telnum":"64884873","depart":"39"},{"id":"485","name":"\u6559\u7814\u5ba4\uff08\u6e05\u6cb3\uff09","telnum":"62844841","depart":"39"},{"id":"486","name":"\u5668\u6750\u5ba4\uff08\u5c0f\u8425\uff09","telnum":"82426139","depart":"39"},{"id":"488","name":"\u4e3b\u4efb\u5ba4","telnum":"82426944","depart":"40"},{"id":"489","name":"\u4e66\u8bb0\u5ba4","telnum":"82426133","depart":"40"},{"id":"490","name":"\u529e\u516c\u5ba4 ","telnum":"82426944","depart":"40"},{"id":"491","name":"\u8ba1\u7b97\u673a\u57fa\u7840\u6559\u7814\u5ba4\uff08\u5c0f\u8425\uff09","telnum":"82427156","depart":"40"},{"id":"492","name":"\u8ba1\u7b97\u673a\u57fa\u7840\u6559\u7814\u5ba4\uff08\u6e05\u6cb3\uff09","telnum":"62844993","depart":"40"},{"id":"493","name":"\u5c0f\u8425\u6821\u533a\u673a\u623f","telnum":"82426945","depart":"40"},{"id":"494","name":"\u5065\u7fd4\u6865\u6821\u533a\u529e\u516c\u5ba4","telnum":"64884743","depart":"40"},{"id":"495","name":"\u5065\u7fd4\u6865\u6821\u533a\u673a\u623f\u503c\u73ed\u5ba4","telnum":"64884742","depart":"40"},{"id":"496","name":"\u5065\u7fd4\u6865\u6821\u533a\u673a\u623f\uff08\u4e8c\u5c42\uff09","telnum":"64889381","depart":"40"},{"id":"497","name":"\u6e05\u6cb3\u6821\u533a\u673a\u623f","telnum":"62844831","depart":"40"},{"id":"499","name":"\u4e3b\u4efb\u5ba4","telnum":"82426948","depart":"41"},{"id":"500","name":"\u529e\u516c\u5ba4","telnum":"82426948","depart":"41"},{"id":"501","name":"\u7535\u5de5\u7535\u5b50\u6559\u5b66\u90e8","telnum":"82426949","depart":"41"},{"id":"502","name":"\u51b7\u52a0\u5de5\u6559\u5b66\u90e8","telnum":"82426950","depart":"41"},{"id":"504","name":"\u4e3b\u4efb\u5ba4","telnum":"64884662","depart":"42"},{"id":"505","name":"\u526f\u4e3b\u4efb\u5ba4","telnum":"64884686","depart":"42"},{"id":"506","name":"\u526f\u4e3b\u4efb\u5ba4","telnum":"64884661","depart":"42"},{"id":"507","name":"\u7ba1\u7406\u529e\u516c\u5ba4","telnum":"64884655","depart":"42"},{"id":"508","name":"\u6821\u533a\u529e\u516c\u5ba4\uff08\u503c\u73ed\u5ba4\uff09","telnum":"64884650","depart":"42"},{"id":"509","name":"\u515a\u52a1\u529e\u516c\u5ba4","telnum":"64884663","depart":"42"},{"id":"510","name":"\u7efc\u5408\u529e\u516c\u5ba4","telnum":"64884657","depart":"42"},{"id":"511","name":"\u5b66\u751f\u5de5\u4f5c\u529e\u516c\u5ba4","telnum":"64884689","depart":"42"},{"id":"512","name":"\u79bb\u9000\u4f11\u529e\u516c\u5ba4","telnum":"64884874","depart":"42"},{"id":"513","name":"\u5bb6\u59d4\u4f1a\u529e\u516c\u5ba4","telnum":"64884872","depart":"42"},{"id":"514","name":"\u4f20\u771f","telnum":"64879080","depart":"42"},{"id":"515","name":"\u7b2c\u4e00\u4f1a\u8bae\u5ba4","telnum":"64884731","depart":"42"},{"id":"516","name":"\u7b2c\u4e8c\u4f1a\u8bae\u5ba4","telnum":"64879609","depart":"42"},{"id":"518","name":"\u4e3b\u4efb\u5ba4","telnum":"62844801","depart":"43"},{"id":"519","name":"\u526f\u4e3b\u4efb\u5ba4","telnum":"62844800","depart":"43"},{"id":"520","name":"\u6821\u533a\u529e\u516c\u5ba4","telnum":"62844802","depart":"43"},{"id":"521","name":"\u7efc\u5408\u7ba1\u7406\u529e\u516c\u5ba4","telnum":"62844803","depart":"43"},{"id":"522","name":"\u4f20\u771f","telnum":"62915980","depart":"43"},{"id":"523","name":"\u4f1a\u8bae\u5ba4","telnum":"62844838","depart":"43"},{"id":"524","name":"\u4f1a\u8bae\u5ba4","telnum":"62922534","depart":"43"},{"id":"526","name":"\u4e3b\u4efb\u5ba4","telnum":"85994588","depart":"44"},{"id":"527","name":"\u6821\u533a\u529e\u516c\u5ba4","telnum":"85992516","depart":"44"},{"id":"528","name":"\u7ef4\u4fee\u7ec4","telnum":"85994303","depart":"44"},{"id":"529","name":"\u6536\u8d39\u5ba4","telnum":"85992263","depart":"44"},{"id":"530","name":"\u5bb6\u59d4\u4f1a","telnum":"85992564","depart":"44"},{"id":"531","name":"\u533b\u52a1\u5ba4","telnum":"85993379","depart":"44"},{"id":"532","name":"\u8d22\u52a1\u5ba4","telnum":"85993799","depart":"44"},{"id":"533","name":"\u5b89\u5168\u4fdd\u536b","telnum":"85994583","depart":"44"},{"id":"535","name":"\u4e3b\u4efb\u5ba4","telnum":"64373982","depart":"45"},{"id":"536","name":"\u6821\u533a\u529e\u516c\u5ba4","telnum":"64373826","depart":"45"},{"id":"537","name":"\u4f20\u771f","telnum":"64373546","depart":"45"},{"id":"538","name":"\u5b89\u5168\u4fdd\u536b","telnum":"64373820","depart":"45"},{"id":"539","name":"\u6536\u53d1\u5ba4","telnum":"64373129","depart":"45"},{"id":"540","name":"\u95e8\u536b","telnum":"64373718","depart":"45"},{"id":"541","name":"\u533b\u52a1\u5ba4","telnum":"64373559","depart":"45"},{"id":"542","name":"\u62a5\u9500\u529e\u516c\u5ba4","telnum":"64378675","depart":"45"},{"id":"544","name":"\u9662\u957f\u5ba4","telnum":"82426894","depart":"46"},{"id":"545","name":"\u526f\u9662\u957f\u5ba4","telnum":"82426896","depart":"46"},{"id":"546","name":"\u591c\u5927\u6559\u5b66\u90e8","telnum":"82426897","depart":"46"},{"id":"547","name":"\u7efc\u5408\u7ba1\u7406\u529e\u516c\u5ba4","telnum":"82426898","depart":"46"},{"id":"548","name":"\u62db\u751f\u4e0e\u57f9\u8bad\u90e8","telnum":"82426899","depart":"46"},{"id":"549","name":"\u591c\u5927\u6559\u5b66\u90e8\uff08\u5c0f\u8425\uff09","telnum":"82427186","depart":"46"},{"id":"550","name":"\u591c\u5927\u6559\u5b66\u90e8\uff08\u5065\u7fd4\u6865\uff09","telnum":"64884675","depart":"46"},{"id":"551","name":"\u591c\u5927\u6559\u5b66\u90e8\uff08\u91d1\u53f0\u8def\uff09","telnum":"85992344","depart":"46"},{"id":"552","name":"\u591c\u5927\u6559\u5b66\u90e8\uff08\u9152\u4ed9\u6865\uff09","telnum":"64389159","depart":"46"},{"id":"554","name":"\u4e3b\u4efb\u5ba4","telnum":"82426885","depart":"47"},{"id":"555","name":"\u526f\u4e3b\u4efb\u5ba4","telnum":"82426887","depart":"47"},{"id":"556","name":"\u529e\u516c\u5ba4","telnum":"82426884","depart":"47"},{"id":"558","name":"\u9986\u957f\u5ba4","telnum":"82426118","depart":"48"},{"id":"559","name":"\u526f\u9986\u957f\u5ba4","telnum":"82426940","depart":"48"},{"id":"560","name":"\u526f\u9986\u957f\u5ba4","telnum":"82426811","depart":"48"},{"id":"561","name":"\u529e\u516c\u5ba4\uff08\u5c0f\u8425\uff09","telnum":"82426940","depart":"48"},{"id":"562","name":"\u529e\u516c\u5ba4\uff08\u5065\u7fd4\u6865\uff09","telnum":"64884728","depart":"48"},{"id":"563","name":"\u91c7\u7f16\u90e8 (\u5065\u7fd4\u6865)","telnum":"64884727","depart":"48"},{"id":"564","name":"\u91c7\u7f16\u90e8(\u5c0f\u8425)","telnum":"82426942","depart":"48"},{"id":"565","name":"\u671f\u520a\u90e8(\u5c0f\u8425)","telnum":"82426116","depart":"48"},{"id":"566","name":"\u671f\u520a\u90e8(\u6e05\u6cb3)","telnum":"62844945","depart":"48"},{"id":"567","name":"\u671f\u520a\u90e8(\u5065\u7fd4\u6865)","telnum":"64884725","depart":"48"},{"id":"568","name":"\u6d41\u901a\u90e8","telnum":"","depart":"48"},{"id":"569","name":"\u5c0f\u8425\u8fd8\u4e66\u5904","telnum":"82426117","depart":"48"},{"id":"570","name":"\u5c0f\u8425\u79d1\u6280\u56fe\u4e66","telnum":"82426943","depart":"48"},{"id":"571","name":"\u5c0f\u8425\u793e\u79d1\u56fe\u4e66","telnum":"82426119","depart":"48"},{"id":"572","name":"\u5065\u7fd4\u6865\u793e\u79d1\u3001\u79d1\u6280\u56fe\u4e66","telnum":"64884724","depart":"48"},{"id":"573","name":"\u6e05\u6cb3\u793e\u79d1\u3001\u79d1\u6280\u56fe\u4e66","telnum":"62844839","depart":"48"},{"id":"574","name":"\u4fe1\u606f\u54a8\u8be2\u90e8","telnum":"","depart":"48"},{"id":"575","name":"\u5c0f\u8425\u7535\u5b50\u9605\u89c8\u5ba4","telnum":"82426941","depart":"48"},{"id":"576","name":"\u5c0f\u8425\u7efc\u5408\u9605\u89c8\u5ba4","telnum":"82426941","depart":"48"},{"id":"577","name":"\u5065\u7fd4\u6865\u6821\u533a","telnum":"64884723","depart":"48"},{"id":"578","name":"\u6e05\u6cb3\u7535\u5b50\u9605\u89c8\u5ba4","telnum":"62844991","depart":"48"},{"id":"579","name":"\u5065\u7fd4\u6865\u7535\u5b50\u9605\u89c8\u5ba4","telnum":"64884726","depart":"48"},{"id":"581","name":"\u4e3b\u4efb\u5ba4","telnum":"82426946","depart":"49"},{"id":"582","name":"\u529e\u516c\u5ba4(\u5c0f\u8425)","telnum":"82426946","depart":"49"},{"id":"583","name":"\u5361\u52a1\u5ba4\uff08\u5c0f\u8425\uff09","telnum":"82426966","depart":"49"},{"id":"584","name":"\u529e\u516c\u5ba4(\u5065\u7fd4\u6865)","telnum":"64884209","depart":"49"},{"id":"585","name":"\u5361\u52a1\u5ba4\uff08\u5065\u7fd4\u6865\uff09","telnum":"64884378","depart":"49"},{"id":"586","name":"\u529e\u516c\u5ba4(\u6e05\u6cb3)","telnum":"62844844","depart":"49"},{"id":"587","name":"\u5361\u52a1\u5ba4\uff08\u6e05\u6cb3\uff09","telnum":"62844840","depart":"49"},{"id":"588","name":"\u6821\u56ed\u5361\u81ea\u52a9\u670d\u52a1\u7535\u8bdd","telnum":"62841188","depart":"49"}]